dirtyR/.DS_Store
dirtyR/__init__.py
dirtyR/smooth.py
dirtyR/turnpoints.py
dirtyR/version.py
dirtyR-0.0.9.dist-info/LICENSE
dirtyR-0.0.9.dist-info/WHEEL
dirtyR-0.0.9.dist-info/METADATA
dirtyR-0.0.9.dist-info/RECORD
