Metadata-Version: 2.1
Name: dirtyR
Version: 0.0.9
Summary: very dirty...
Home-page: https://github.com/bchaselab/dirtyR
License: UNKNOWN
Author: fcatus
Author-email: f.catus@pm.me
Requires-Python: >=3.6
Classifier: License :: OSI Approved :: MIT License
Classifier: Programming Language :: Python :: 3
